{
"generatedAt": "2026-03-27T12:13:28Z",
"location": "Grove (Cygnet Area)",
"coordinates": "-43.1647,147.0584",
"currentConditions": {
  "temperature": "7.1",
  "apparentTemperature": "5.8",
  "humidity": "93",
  "windDirection": "N",
  "windSpeed": "2",
  "windGust": "6",
  "pressure": "N/A",
  "rainfall": "0.0",
  "conditions": "-",
  "emoji": "☀️",
  "comfort": "Cold ❄️"
},
"analytics": {
  "weatherQuality": "moderate",
  "dataSource": "Australian Bureau of Meteorology",
  "observationTime": "20260327120000",
  "systemVersion": "v2.0",
  "updateFrequency": "Every 3 hours",
  "automationLevel": "Fully Automated"
},
"visualizations": {
  "temperatureBar": "█░░░░░░░░░",
  "humidityBar": "█████████░",
  "windBar": "█░░░░░░░░░░"
},
"insights": [
  "🌡️ Temperature monitoring active",
  "💨 Wind pattern analysis operational",
  "💧 Humidity tracking comprehensive",
  "🌧️ Precipitation monitoring real-time"
]
}
