{
"generatedAt": "2026-04-21T15:31:36Z",
"location": "Grove (Cygnet Area)",
"coordinates": "-43.1647,147.0584",
"currentConditions": {
  "temperature": "5.3",
  "apparentTemperature": "2.8",
  "humidity": "97",
  "windDirection": "ENE",
  "windSpeed": "7",
  "windGust": "11",
  "pressure": "N/A",
  "rainfall": "0.0",
  "conditions": "-",
  "emoji": "☀️",
  "comfort": "Cold ❄️"
},
"analytics": {
  "weatherQuality": "moderate",
  "dataSource": "Australian Bureau of Meteorology",
  "observationTime": "20260421150000",
  "systemVersion": "v2.0",
  "updateFrequency": "Every 3 hours",
  "automationLevel": "Fully Automated"
},
"visualizations": {
  "temperatureBar": "█░░░░░░░░░",
  "humidityBar": "█████████░",
  "windBar": "█░░░░░░░░░"
},
"insights": [
  "🌡️ Temperature monitoring active",
  "💨 Wind pattern analysis operational",
  "💧 Humidity tracking comprehensive",
  "🌧️ Precipitation monitoring real-time"
]
}
