{
"generatedAt": "2026-04-25T21:11:16Z",
"location": "Grove (Cygnet Area)",
"coordinates": "-43.1647,147.0584",
"currentConditions": {
  "temperature": "9.2",
  "apparentTemperature": "7.5",
  "humidity": "89",
  "windDirection": "W",
  "windSpeed": "6",
  "windGust": "9",
  "pressure": "N/A",
  "rainfall": "0.0",
  "conditions": "-",
  "emoji": "☀️",
  "comfort": "Cold ❄️"
},
"analytics": {
  "weatherQuality": "moderate",
  "dataSource": "Australian Bureau of Meteorology",
  "observationTime": "20260425210000",
  "systemVersion": "v2.0",
  "updateFrequency": "Every 3 hours",
  "automationLevel": "Fully Automated"
},
"visualizations": {
  "temperatureBar": "██░░░░░░░░",
  "humidityBar": "████████░░",
  "windBar": "█░░░░░░░░░"
},
"insights": [
  "🌡️ Temperature monitoring active",
  "💨 Wind pattern analysis operational",
  "💧 Humidity tracking comprehensive",
  "🌧️ Precipitation monitoring real-time"
]
}
