{
"station": "Grove (Cygnet Area)",
"coordinates": "-43.1647,147.0584",
"temperature": "9.7",
"apparent_temperature": "9.1",
"humidity": "95",
"wind_direction": "NE",
"wind_speed_kmh": "2",
"wind_gust_kmh": "7",
"pressure_hpa": "N/A",
"rainfall_mm": "0.0",
"conditions": "-",
"weather_emoji": "☀️",
"comfort_level": "Cold ❄️",
"observation_time": "20260322150000",
"updated_at": "2026-03-22T15:05:37Z",
"visualizations": {
  "temperature_bar": "██░░░░░░░░",
  "humidity_bar": "█████████░",
  "wind_bar": "█░░░░░░░░░░"
}
}
