{
"station": "Grove (Cygnet Area)",
"coordinates": "-43.1647,147.0584",
"temperature": "12.8",
"apparent_temperature": "13.0",
"humidity": "87",
"wind_direction": "CALM",
"wind_speed_kmh": "0",
"wind_gust_kmh": "0",
"pressure_hpa": "N/A",
"rainfall_mm": "0.0",
"conditions": "-",
"weather_emoji": "☀️",
"comfort_level": "Perfect 😌",
"observation_time": "20260330090000",
"updated_at": "2026-03-30T09:29:45Z",
"visualizations": {
  "temperature_bar": "███░░░░░░░",
  "humidity_bar": "████████░░",
  "wind_bar": "█░░░░░░░░░░"
}
}
