{
"station": "Grove (Cygnet Area)",
"coordinates": "-43.1647,147.0584",
"temperature": "15.2",
"apparent_temperature": "14.3",
"humidity": "75",
"wind_direction": "ENE",
"wind_speed_kmh": "6",
"wind_gust_kmh": "11",
"pressure_hpa": "N/A",
"rainfall_mm": "0.0",
"conditions": "-",
"weather_emoji": "☀️",
"comfort_level": "Perfect 😌",
"observation_time": "20260318090000",
"updated_at": "2026-03-18T09:17:59Z",
"visualizations": {
  "temperature_bar": "███░░░░░░░",
  "humidity_bar": "███████░░░",
  "wind_bar": "█░░░░░░░░░"
}
}
