{
"station": "Grove (Cygnet Area)",
"coordinates": "-43.1647,147.0584",
"temperature": "15.4",
"apparent_temperature": "13.7",
"humidity": "69",
"wind_direction": "ESE",
"wind_speed_kmh": "9",
"wind_gust_kmh": "17",
"pressure_hpa": "N/A",
"rainfall_mm": "0.0",
"conditions": "-",
"weather_emoji": "☀️",
"comfort_level": "Perfect 😌",
"observation_time": "20260303090000",
"updated_at": "2026-03-03T09:13:41Z",
"visualizations": {
  "temperature_bar": "███░░░░░░░",
  "humidity_bar": "██████░░░░",
  "wind_bar": "█░░░░░░░░░"
}
}
